{
  "collectionName": "components_franchise_commitments",
  "info": {
    "name": "commitment",
    "icon": "award"
  },
  "options": {},
  "attributes": {
    "title": {
      "type": "string"
    },
    "subDescription": {
      "type": "string"
    },
    "description": {
      "type": "text"
    },
    "button": {
      "type": "component",
      "repeatable": false,
      "component": "custom.button"
    },
    "image": {
      "model": "file",
      "via": "related",
      "allowedTypes": [
        "images",
        "files",
        "videos"
      ],
      "plugin": "upload",
      "required": false,
      "pluginOptions": {}
    }
  }
}
